virtualinput/__init__.py
virtualinput/keyboard.py
virtualinput/mouse.py
virtualinput/recorder.py
virtualinput/core/__init__.py
virtualinput/core/base_classes.py
virtualinput/core/exceptions.py
virtualinput/core/keycodes.py
virtualinput/core/utils.py
virtualinput/platforms/__init__.py
virtualinput/platforms/macos/__init__.py
virtualinput/platforms/macos/keyboard.py
virtualinput/platforms/macos/mouse.py
virtualinput/platforms/macos/utils.py
virtualinput/platforms/windows/__init__.py
virtualinput/platforms/windows/keyboard.py
virtualinput/platforms/windows/mouse.py
virtualinput/platforms/windows/utils.py
virtualinput-1.0.2.dist-info/METADATA
virtualinput-1.0.2.dist-info/WHEEL
virtualinput-1.0.2.dist-info/top_level.txt
virtualinput-1.0.2.dist-info/RECORD
