Metadata-Version: 2.4
Name: virtualinput
Version: 1.0.2
Summary: Cross-platform virtual mouse and keyboard with ghost coordinates and Bézier curves
Home-page: https://github.com/off-rkv/Virtual-Input
Author: off.rkv
Author-email: off.rkv@gmail.com
Classifier: Programming Language :: Python :: 3
Classifier: License :: OSI Approved :: MIT License
Classifier: Operating System :: OS Independent
Requires-Python: >=3.7
Dynamic: author
Dynamic: author-email
Dynamic: classifier
Dynamic: description
Dynamic: description-content-type
Dynamic: home-page
Dynamic: requires-python
Dynamic: summary
